mizuku/__init__.py
mizuku/main.py
mizuku/mizu.py
mizuku-1.1.2.dist-info/METADATA
mizuku-1.1.2.dist-info/WHEEL
mizuku-1.1.2.dist-info/entry_points.txt
mizuku-1.1.2.dist-info/licenses/LICENSE
mizuku-1.1.2.dist-info/RECORD
